lawgorithm/__init__.py
lawgorithm/client.py
lawgorithm/exceptions.py
lawgorithm/models.py
lawgorithm-0.1.0.dist-info/METADATA
lawgorithm-0.1.0.dist-info/WHEEL
lawgorithm-0.1.0.dist-info/licenses/LICENSE
lawgorithm-0.1.0.dist-info/RECORD
