Metadata-Version: 2.4
Name: lawgorithm
Version: 0.1.0
Summary: Python SDK for Lawgorithm - AI Act Compliance Platform
Project-URL: Homepage, https://lawgorithm.io
Project-URL: Documentation, https://docs.lawgorithm.io
Project-URL: Repository, https://github.com/arielibaba/lawgorithm-python
Project-URL: Issues, https://github.com/arielibaba/lawgorithm-python/issues
Author-email: Lawgorithm <contact@lawgorithm.io>
License: MIT
License-File: LICENSE
Keywords: ai-act,ai-governance,compliance,eu-regulation,mlops
Classifier: Development Status :: 4 - Beta
Classifier: Intended Audience :: Developers
Classifier: License :: OSI Approved :: MIT License
Classifier: Programming Language :: Python :: 3
Classifier: Programming Language :: Python :: 3.10
Classifier: Programming Language :: Python :: 3.11
Classifier: Programming Language :: Python :: 3.12
Classifier: Topic :: Scientific/Engineering :: Artificial Intelligence
Classifier: Topic :: Software Development :: Libraries :: Python Modules
Requires-Python: >=3.10
Requires-Dist: httpx>=0.25.0
Requires-Dist: pydantic>=2.0.0
Provides-Extra: dev
Requires-Dist: mypy>=1.13.0; extra == 'dev'
Requires-Dist: pytest-asyncio>=0.24.0; extra == 'dev'
Requires-Dist: pytest-httpx>=0.30.0; extra == 'dev'
Requires-Dist: pytest>=8.0.0; extra == 'dev'
Requires-Dist: ruff>=0.8.0; extra == 'dev'
